{
  "product_id": "KGEN-12345-HEART-UI",
  "current_version": "V10.40.5_MIRROR_CENTER_BULLBEAR_RESTORE",
  "build": "20260518-V10.40.5-MIRROR-CENTER-BULLBEAR-RESTORE",
  "base_from": "KGEN-12345-V10.40.4_NO_WHITEWORK_COUNTDOWN_UI_FIX",
  "canonical_path": "K線西遊記/temples/12345/index.html",
  "root_bridges": [
    "12345.html",
    "wallet-12345.html"
  ],
  "asset_manifest": "V10.27.1 official asset names only",
  "official_assets": [
    "assets/bull-front.png",
    "assets/bear-rear.png",
    "assets/heart.png",
    "assets/warp-core.png"
  ],
  "fixed": [
    "removed active legacy wukong_heart_v10_4.png dependency",
    "removed active legacy wukong_heart_core.jpg / wukong_caishen.png fallback dependency",
    "updated install-check required asset to assets/heart.png",
    "preserved left-bottom MOVE joystick and V9 recorder core",
    "added mobile safe layout patch for central core, panels, HUD, joystick and elevator",
    "converted root 12345.html into bridge file only",
    "updated wallet-12345.html bridge version"
  ],
  "version": "KGEN-12345-V10.40.5_MIRROR_CENTER_BULLBEAR_RESTORE",
  "rules": [
    "do not retune broken legacy countdown blocks",
    "hide old countdown and rebuild compact strip",
    "preserve joystick",
    "preserve wallet and contract wiring",
    "do not overwrite official assets"
  ],
  "patch_scope": [
    "central core transform-origin fixed",
    "bull/bear image switching restored",
    "legacy debug text suppressed",
    "joystick preserved",
    "wallet/contract unchanged"
  ]
}